slvcodec/__init__.py
slvcodec/cocotb_dut.py
slvcodec/cocotb_helper.py
slvcodec/config.py
slvcodec/conversions.py
slvcodec/dependencies.py
slvcodec/entity.py
slvcodec/event.py
slvcodec/filetestbench_generator.py
slvcodec/flatten_generator.py
slvcodec/fusesoc_wrapper.py
slvcodec/inner_vhdl_parser.py
slvcodec/math_parser.py
slvcodec/package.py
slvcodec/package_generator.py
slvcodec/resolution.py
slvcodec/test_utils.py
slvcodec/typ_parser.py
slvcodec/typs.py
slvcodec/version.py
slvcodec/vhdl_parser.py
slvcodec/cocotb_wrapper/__init__.py
slvcodec/cocotb_wrapper/result.py
slvcodec/cocotb_wrapper/triggers.py
slvcodec/templates/file_testbench.vhd
slvcodec/templates/file_testbench_multiple_clocks.vhd
slvcodec/templates/file_testbench_no_vunit.vhd
slvcodec/templates/flatten.vhd
slvcodec/templates/formal_pkg.vhd
slvcodec/templates/formal_wrapper.vhd
slvcodec/templates/fromslvcodec.vhd
slvcodec/templates/pipe_testbench.vhd
slvcodec/templates/setgenerics.vhd
slvcodec/templates/setgenerics_not_slv.vhd
slvcodec/templates/setgenerics_pkg.vhd
slvcodec/templates/slvcodec_array_template.vhd
slvcodec/templates/slvcodec_enumeration_template.vhd
slvcodec/templates/slvcodec_record_template.vhd
slvcodec/templates/toslvcodec.vhd
slvcodec/vhdl/clock.vhd
slvcodec/vhdl/read_file.vhd
slvcodec/vhdl/read_file_no_vunit.vhd
slvcodec/vhdl/read_pipe.vhd
slvcodec/vhdl/slvcodec.vhd
slvcodec/vhdl/txt_util.vhd
slvcodec/vhdl/write_file.vhd
slvcodec/vhdl/write_pipe.vhd
slvcodec-0.4.20.dist-info/METADATA
slvcodec-0.4.20.dist-info/WHEEL
slvcodec-0.4.20.dist-info/top_level.txt
slvcodec-0.4.20.dist-info/RECORD
