Metadata-Version: 2.2
Name: slvcodec
Version: 0.4.20
Summary: Utilities for generating VHDL to convert to and from std_logic_vector, as well as utilties to create testbenches described by python.
Home-page: https://github.com/benreynwar/slvcodec
Author: Ben Reynwar
Author-email: ben@reynwar.net
License: MIT
Keywords: VHDL,hdl,rtl,FPGA,ASIC,Xilinx,Altera
Requires-Dist: jinja2>=2.8
Requires-Dist: pytest
Requires-Dist: vunit-hdl
Requires-Dist: pyyaml
Requires-Dist: cocotb>=1.4.0rc1
Requires-Dist: fusesoc
Dynamic: author
Dynamic: author-email
Dynamic: description
Dynamic: description-content-type
Dynamic: home-page
Dynamic: keywords
Dynamic: license
Dynamic: requires-dist
Dynamic: summary
